troposphere_dns_certificate/__init__.py
troposphere_dns_certificate/certificate.py
troposphere_dns_certificate/certificatemanager.py
troposphere_dns_certificate-2.0.0.dist-info/LICENSE
troposphere_dns_certificate-2.0.0.dist-info/METADATA
troposphere_dns_certificate-2.0.0.dist-info/WHEEL
troposphere_dns_certificate-2.0.0.dist-info/top_level.txt
troposphere_dns_certificate-2.0.0.dist-info/RECORD
