Metadata-Version: 2.1
Name: troposphere-dns-certificate
Version: 2.0.0
Summary: Cloudformation DNS validated certificate resource for troposphere
Home-page: https://github.com/dflook/cloudformation-dns-certificate
Author: Daniel Flook
Author-email: daniel@flook.org
License: MIT
Project-URL: Issues, https://github.com/dflook/cloudformation-dns-certificate/issues
Keywords: cloudformation troposphere certificate
License-File: LICENSE
Requires-Dist: troposphere (>=4.3.1)
Requires-Dist: awacs
Requires-Dist: wrapt
Requires-Dist: python-minifier (>=2.3.0)
Requires-Dist: boto3
